{"county_fips":"08007","county_name":"archuleta, co","timeseries":[{"county_fips":"08007","median_listing_price":"714500","month_date_yyyymm":"2025-03-01"},{"county_fips":"08007","median_listing_price":"698500","month_date_yyyymm":"2025-02-01"},{"county_fips":"08007","median_listing_price":"703000","month_date_yyyymm":"2025-01-01"},{"county_fips":"08007","median_listing_price":"710995","month_date_yyyymm":"2024-12-01"},{"county_fips":"08007","median_listing_price":"699000","month_date_yyyymm":"2024-11-01"},{"county_fips":"08007","median_listing_price":"695000","month_date_yyyymm":"2024-10-01"},{"county_fips":"08007","median_listing_price":"687450","month_date_yyyymm":"2024-09-01"},{"county_fips":"08007","median_listing_price":"703500","month_date_yyyymm":"2024-08-01"},{"county_fips":"08007","median_listing_price":"751950","month_date_yyyymm":"2024-07-01"},{"county_fips":"08007","median_listing_price":"752450","month_date_yyyymm":"2024-06-01"},{"county_fips":"08007","median_listing_price":"749450","month_date_yyyymm":"2024-05-01"},{"county_fips":"08007","median_listing_price":"787350","month_date_yyyymm":"2024-04-01"},{"county_fips":"08007","median_listing_price":"775000","month_date_yyyymm":"2024-03-01"},{"county_fips":"08007","median_listing_price":"763500","month_date_yyyymm":"2024-02-01"},{"county_fips":"08007","median_listing_price":"799225","month_date_yyyymm":"2024-01-01"},{"county_fips":"08007","median_listing_price":"795000","month_date_yyyymm":"2023-12-01"},{"county_fips":"08007","median_listing_price":"795000","month_date_yyyymm":"2023-11-01"},{"county_fips":"08007","median_listing_price":"796000","month_date_yyyymm":"2023-10-01"},{"county_fips":"08007","median_listing_price":"795000","month_date_yyyymm":"2023-09-01"},{"county_fips":"08007","median_listing_price":"799000","month_date_yyyymm":"2023-08-01"},{"county_fips":"08007","median_listing_price":"790000","month_date_yyyymm":"2023-07-01"},{"county_fips":"08007","median_listing_price":"811750","month_date_yyyymm":"2023-06-01"},{"county_fips":"08007","median_listing_price":"849000","month_date_yyyymm":"2023-05-01"},{"county_fips":"08007","median_listing_price":"849000","month_date_yyyymm":"2023-04-01"},{"county_fips":"08007","median_listing_price":"868500","month_date_yyyymm":"2023-03-01"}]}