{"county_fips":"08097","county_name":"pitkin, co","timeseries":[{"county_fips":"08097","median_listing_price":"3650000","month_date_yyyymm":"2025-03-01"},{"county_fips":"08097","median_listing_price":"3737500","month_date_yyyymm":"2025-02-01"},{"county_fips":"08097","median_listing_price":"3750000","month_date_yyyymm":"2025-01-01"},{"county_fips":"08097","median_listing_price":"3318750","month_date_yyyymm":"2024-12-01"},{"county_fips":"08097","median_listing_price":"2847500","month_date_yyyymm":"2024-11-01"},{"county_fips":"08097","median_listing_price":"2936250","month_date_yyyymm":"2024-10-01"},{"county_fips":"08097","median_listing_price":"3193500","month_date_yyyymm":"2024-09-01"},{"county_fips":"08097","median_listing_price":"3200000","month_date_yyyymm":"2024-08-01"},{"county_fips":"08097","median_listing_price":"3093750","month_date_yyyymm":"2024-07-01"},{"county_fips":"08097","median_listing_price":"2733540","month_date_yyyymm":"2024-06-01"},{"county_fips":"08097","median_listing_price":"1873750","month_date_yyyymm":"2024-05-01"},{"county_fips":"08097","median_listing_price":"2199125","month_date_yyyymm":"2024-04-01"},{"county_fips":"08097","median_listing_price":"2495000","month_date_yyyymm":"2024-03-01"},{"county_fips":"08097","median_listing_price":"2517385","month_date_yyyymm":"2024-02-01"},{"county_fips":"08097","median_listing_price":"2733750","month_date_yyyymm":"2024-01-01"},{"county_fips":"08097","median_listing_price":"2605000","month_date_yyyymm":"2023-12-01"},{"county_fips":"08097","median_listing_price":"2753844","month_date_yyyymm":"2023-11-01"},{"county_fips":"08097","median_listing_price":"2962500","month_date_yyyymm":"2023-10-01"},{"county_fips":"08097","median_listing_price":"3395000","month_date_yyyymm":"2023-09-01"},{"county_fips":"08097","median_listing_price":"3495000","month_date_yyyymm":"2023-08-01"},{"county_fips":"08097","median_listing_price":"3495000","month_date_yyyymm":"2023-07-01"},{"county_fips":"08097","median_listing_price":"3225000","month_date_yyyymm":"2023-06-01"},{"county_fips":"08097","median_listing_price":"3037500","month_date_yyyymm":"2023-05-01"},{"county_fips":"08097","median_listing_price":"2798000","month_date_yyyymm":"2023-04-01"},{"county_fips":"08097","median_listing_price":"2626250","month_date_yyyymm":"2023-03-01"}]}