{"county_fips":"29045","county_name":"clark, mo","timeseries":[{"county_fips":"29045","median_listing_price":"132000","month_date_yyyymm":"2025-03-01"},{"county_fips":"29045","median_listing_price":"134250","month_date_yyyymm":"2025-02-01"},{"county_fips":"29045","median_listing_price":"129900","month_date_yyyymm":"2025-01-01"},{"county_fips":"29045","median_listing_price":"300000","month_date_yyyymm":"2024-12-01"},{"county_fips":"29045","median_listing_price":"310000","month_date_yyyymm":"2024-11-01"},{"county_fips":"29045","median_listing_price":"349000","month_date_yyyymm":"2024-10-01"},{"county_fips":"29045","median_listing_price":"435613","month_date_yyyymm":"2024-09-01"},{"county_fips":"29045","median_listing_price":"375000","month_date_yyyymm":"2024-08-01"},{"county_fips":"29045","median_listing_price":"329500","month_date_yyyymm":"2024-07-01"},{"county_fips":"29045","median_listing_price":"307450","month_date_yyyymm":"2024-06-01"},{"county_fips":"29045","median_listing_price":"239900","month_date_yyyymm":"2024-05-01"},{"county_fips":"29045","median_listing_price":"178475","month_date_yyyymm":"2024-04-01"},{"county_fips":"29045","median_listing_price":"198950","month_date_yyyymm":"2024-03-01"},{"county_fips":"29045","median_listing_price":"290725","month_date_yyyymm":"2024-02-01"},{"county_fips":"29045","median_listing_price":"259700","month_date_yyyymm":"2024-01-01"},{"county_fips":"29045","median_listing_price":"262450","month_date_yyyymm":"2023-12-01"},{"county_fips":"29045","median_listing_price":"232475","month_date_yyyymm":"2023-11-01"},{"county_fips":"29045","median_listing_price":"200000","month_date_yyyymm":"2023-10-01"},{"county_fips":"29045","median_listing_price":"171000","month_date_yyyymm":"2023-09-01"},{"county_fips":"29045","median_listing_price":"171500","month_date_yyyymm":"2023-08-01"},{"county_fips":"29045","median_listing_price":"204450","month_date_yyyymm":"2023-07-01"},{"county_fips":"29045","median_listing_price":"197175","month_date_yyyymm":"2023-06-01"},{"county_fips":"29045","median_listing_price":"189900","month_date_yyyymm":"2023-05-01"},{"county_fips":"29045","median_listing_price":"297250","month_date_yyyymm":"2023-04-01"},{"county_fips":"29045","median_listing_price":"299999","month_date_yyyymm":"2023-03-01"}]}