{"county_fips":"46093","county_name":"meade, sd","timeseries":[{"county_fips":"46093","median_listing_price":"484250","month_date_yyyymm":"2025-03-01"},{"county_fips":"46093","median_listing_price":"488375","month_date_yyyymm":"2025-02-01"},{"county_fips":"46093","median_listing_price":"475000","month_date_yyyymm":"2025-01-01"},{"county_fips":"46093","median_listing_price":"480975","month_date_yyyymm":"2024-12-01"},{"county_fips":"46093","median_listing_price":"479000","month_date_yyyymm":"2024-11-01"},{"county_fips":"46093","median_listing_price":"492950","month_date_yyyymm":"2024-10-01"},{"county_fips":"46093","median_listing_price":"488250","month_date_yyyymm":"2024-09-01"},{"county_fips":"46093","median_listing_price":"492500","month_date_yyyymm":"2024-08-01"},{"county_fips":"46093","median_listing_price":"481425","month_date_yyyymm":"2024-07-01"},{"county_fips":"46093","median_listing_price":"469900","month_date_yyyymm":"2024-06-01"},{"county_fips":"46093","median_listing_price":"479950","month_date_yyyymm":"2024-05-01"},{"county_fips":"46093","median_listing_price":"506950","month_date_yyyymm":"2024-04-01"},{"county_fips":"46093","median_listing_price":"459900","month_date_yyyymm":"2024-03-01"},{"county_fips":"46093","median_listing_price":"463900","month_date_yyyymm":"2024-02-01"},{"county_fips":"46093","median_listing_price":"473900","month_date_yyyymm":"2024-01-01"},{"county_fips":"46093","median_listing_price":"459900","month_date_yyyymm":"2023-12-01"},{"county_fips":"46093","median_listing_price":"478900","month_date_yyyymm":"2023-11-01"},{"county_fips":"46093","median_listing_price":"492225","month_date_yyyymm":"2023-10-01"},{"county_fips":"46093","median_listing_price":"469900","month_date_yyyymm":"2023-09-01"},{"county_fips":"46093","median_listing_price":"526950","month_date_yyyymm":"2023-08-01"},{"county_fips":"46093","median_listing_price":"565000","month_date_yyyymm":"2023-07-01"},{"county_fips":"46093","median_listing_price":"574450","month_date_yyyymm":"2023-06-01"},{"county_fips":"46093","median_listing_price":"571925","month_date_yyyymm":"2023-05-01"},{"county_fips":"46093","median_listing_price":"594950","month_date_yyyymm":"2023-04-01"},{"county_fips":"46093","median_listing_price":"526200","month_date_yyyymm":"2023-03-01"},{"county_fips":"46093","median_listing_price":"499900","month_date_yyyymm":"2023-02-01"},{"county_fips":"46093","median_listing_price":"493839","month_date_yyyymm":"2023-01-01"},{"county_fips":"46093","median_listing_price":"498389","month_date_yyyymm":"2022-12-01"},{"county_fips":"46093","median_listing_price":"495808","month_date_yyyymm":"2022-11-01"},{"county_fips":"46093","median_listing_price":"473839","month_date_yyyymm":"2022-10-01"},{"county_fips":"46093","median_listing_price":"499900","month_date_yyyymm":"2022-09-01"},{"county_fips":"46093","median_listing_price":"497400","month_date_yyyymm":"2022-08-01"},{"county_fips":"46093","median_listing_price":"542750","month_date_yyyymm":"2022-07-01"},{"county_fips":"46093","median_listing_price":"444700","month_date_yyyymm":"2022-06-01"},{"county_fips":"46093","median_listing_price":"438425","month_date_yyyymm":"2022-05-01"},{"county_fips":"46093","median_listing_price":"619000","month_date_yyyymm":"2022-04-01"},{"county_fips":"46093","median_listing_price":"569000","month_date_yyyymm":"2022-03-01"},{"county_fips":"46093","median_listing_price":"429725","month_date_yyyymm":"2022-02-01"},{"county_fips":"46093","median_listing_price":"482250","month_date_yyyymm":"2022-01-01"},{"county_fips":"46093","median_listing_price":"456175","month_date_yyyymm":"2021-12-01"},{"county_fips":"46093","median_listing_price":"492175","month_date_yyyymm":"2021-11-01"},{"county_fips":"46093","median_listing_price":"400000","month_date_yyyymm":"2021-10-01"},{"county_fips":"46093","median_listing_price":"462500","month_date_yyyymm":"2021-09-01"},{"county_fips":"46093","median_listing_price":"426875","month_date_yyyymm":"2021-08-01"},{"county_fips":"46093","median_listing_price":"389900","month_date_yyyymm":"2021-07-01"},{"county_fips":"46093","median_listing_price":"343500","month_date_yyyymm":"2021-06-01"},{"county_fips":"46093","median_listing_price":"339500","month_date_yyyymm":"2021-05-01"},{"county_fips":"46093","median_listing_price":"278725","month_date_yyyymm":"2021-04-01"},{"county_fips":"46093","median_listing_price":"186000","month_date_yyyymm":"2021-03-01"},{"county_fips":"46093","median_listing_price":"186000","month_date_yyyymm":"2021-02-01"},{"county_fips":"46093","median_listing_price":"186000","month_date_yyyymm":"2021-01-01"},{"county_fips":"46093","median_listing_price":"327425","month_date_yyyymm":"2020-12-01"},{"county_fips":"46093","median_listing_price":"380550","month_date_yyyymm":"2020-11-01"},{"county_fips":"46093","median_listing_price":"369900","month_date_yyyymm":"2020-10-01"},{"county_fips":"46093","median_listing_price":"392325","month_date_yyyymm":"2020-09-01"},{"county_fips":"46093","median_listing_price":"399500","month_date_yyyymm":"2020-08-01"},{"county_fips":"46093","median_listing_price":"375950","month_date_yyyymm":"2020-07-01"},{"county_fips":"46093","median_listing_price":"387450","month_date_yyyymm":"2020-06-01"},{"county_fips":"46093","median_listing_price":"369900","month_date_yyyymm":"2020-05-01"},{"county_fips":"46093","median_listing_price":"334900","month_date_yyyymm":"2020-04-01"},{"county_fips":"46093","median_listing_price":"347050","month_date_yyyymm":"2020-03-01"},{"county_fips":"46093","median_listing_price":"334900","month_date_yyyymm":"2020-02-01"},{"county_fips":"46093","median_listing_price":"315000","month_date_yyyymm":"2020-01-01"},{"county_fips":"46093","median_listing_price":"277000","month_date_yyyymm":"2019-12-01"},{"county_fips":"46093","median_listing_price":"259900","month_date_yyyymm":"2019-11-01"},{"county_fips":"46093","median_listing_price":"249900","month_date_yyyymm":"2019-10-01"},{"county_fips":"46093","median_listing_price":"256264","month_date_yyyymm":"2019-09-01"},{"county_fips":"46093","median_listing_price":"264445","month_date_yyyymm":"2019-08-01"},{"county_fips":"46093","median_listing_price":"271338","month_date_yyyymm":"2019-07-01"},{"county_fips":"46093","median_listing_price":"269900","month_date_yyyymm":"2019-06-01"},{"county_fips":"46093","median_listing_price":"267400","month_date_yyyymm":"2019-05-01"},{"county_fips":"46093","median_listing_price":"266329","month_date_yyyymm":"2019-04-01"},{"county_fips":"46093","median_listing_price":"261329","month_date_yyyymm":"2019-03-01"}]}