{"county_fips":"48177","county_name":"gonzales, tx","timeseries":[{"county_fips":"48177","median_listing_price":"329950","month_date_yyyymm":"2025-03-01"},{"county_fips":"48177","median_listing_price":"312500","month_date_yyyymm":"2025-02-01"},{"county_fips":"48177","median_listing_price":"315000","month_date_yyyymm":"2025-01-01"},{"county_fips":"48177","median_listing_price":"299900","month_date_yyyymm":"2024-12-01"},{"county_fips":"48177","median_listing_price":"299900","month_date_yyyymm":"2024-11-01"},{"county_fips":"48177","median_listing_price":"275000","month_date_yyyymm":"2024-10-01"},{"county_fips":"48177","median_listing_price":"277000","month_date_yyyymm":"2024-09-01"},{"county_fips":"48177","median_listing_price":"275000","month_date_yyyymm":"2024-08-01"},{"county_fips":"48177","median_listing_price":"253000","month_date_yyyymm":"2024-07-01"},{"county_fips":"48177","median_listing_price":"255000","month_date_yyyymm":"2024-06-01"},{"county_fips":"48177","median_listing_price":"272500","month_date_yyyymm":"2024-05-01"},{"county_fips":"48177","median_listing_price":"265000","month_date_yyyymm":"2024-04-01"},{"county_fips":"48177","median_listing_price":"287450","month_date_yyyymm":"2024-03-01"},{"county_fips":"48177","median_listing_price":"298500","month_date_yyyymm":"2024-02-01"},{"county_fips":"48177","median_listing_price":"312500","month_date_yyyymm":"2024-01-01"},{"county_fips":"48177","median_listing_price":"312000","month_date_yyyymm":"2023-12-01"},{"county_fips":"48177","median_listing_price":"315872","month_date_yyyymm":"2023-11-01"},{"county_fips":"48177","median_listing_price":"309872","month_date_yyyymm":"2023-10-01"},{"county_fips":"48177","median_listing_price":"300000","month_date_yyyymm":"2023-09-01"},{"county_fips":"48177","median_listing_price":"298500","month_date_yyyymm":"2023-08-01"},{"county_fips":"48177","median_listing_price":"295000","month_date_yyyymm":"2023-07-01"},{"county_fips":"48177","median_listing_price":"300000","month_date_yyyymm":"2023-06-01"},{"county_fips":"48177","median_listing_price":"299000","month_date_yyyymm":"2023-05-01"},{"county_fips":"48177","median_listing_price":"295000","month_date_yyyymm":"2023-04-01"},{"county_fips":"48177","median_listing_price":"287500","month_date_yyyymm":"2023-03-01"},{"county_fips":"48177","median_listing_price":"287500","month_date_yyyymm":"2023-02-01"},{"county_fips":"48177","median_listing_price":"228250","month_date_yyyymm":"2023-01-01"},{"county_fips":"48177","median_listing_price":"310000","month_date_yyyymm":"2022-12-01"},{"county_fips":"48177","median_listing_price":"343260","month_date_yyyymm":"2022-11-01"},{"county_fips":"48177","median_listing_price":"336630","month_date_yyyymm":"2022-10-01"},{"county_fips":"48177","median_listing_price":"289250","month_date_yyyymm":"2022-09-01"},{"county_fips":"48177","median_listing_price":"335750","month_date_yyyymm":"2022-08-01"},{"county_fips":"48177","median_listing_price":"339000","month_date_yyyymm":"2022-07-01"},{"county_fips":"48177","median_listing_price":"305563","month_date_yyyymm":"2022-06-01"},{"county_fips":"48177","median_listing_price":"346750","month_date_yyyymm":"2022-05-01"},{"county_fips":"48177","median_listing_price":"275000","month_date_yyyymm":"2022-04-01"},{"county_fips":"48177","median_listing_price":"235000","month_date_yyyymm":"2022-03-01"},{"county_fips":"48177","median_listing_price":"193750","month_date_yyyymm":"2022-02-01"},{"county_fips":"48177","median_listing_price":"210000","month_date_yyyymm":"2022-01-01"},{"county_fips":"48177","median_listing_price":"231000","month_date_yyyymm":"2021-12-01"},{"county_fips":"48177","median_listing_price":"275000","month_date_yyyymm":"2021-11-01"},{"county_fips":"48177","median_listing_price":"318500","month_date_yyyymm":"2021-10-01"},{"county_fips":"48177","median_listing_price":"234375","month_date_yyyymm":"2021-09-01"},{"county_fips":"48177","median_listing_price":"222083","month_date_yyyymm":"2021-08-01"},{"county_fips":"48177","median_listing_price":"294500","month_date_yyyymm":"2021-07-01"},{"county_fips":"48177","median_listing_price":"283649","month_date_yyyymm":"2021-06-01"},{"county_fips":"48177","median_listing_price":"287470","month_date_yyyymm":"2021-05-01"},{"county_fips":"48177","median_listing_price":"256450","month_date_yyyymm":"2021-04-01"},{"county_fips":"48177","median_listing_price":"237460","month_date_yyyymm":"2021-03-01"},{"county_fips":"48177","median_listing_price":"212975","month_date_yyyymm":"2021-02-01"},{"county_fips":"48177","median_listing_price":"207450","month_date_yyyymm":"2021-01-01"},{"county_fips":"48177","median_listing_price":"218500","month_date_yyyymm":"2020-12-01"},{"county_fips":"48177","median_listing_price":"231375","month_date_yyyymm":"2020-11-01"},{"county_fips":"48177","median_listing_price":"215000","month_date_yyyymm":"2020-10-01"},{"county_fips":"48177","median_listing_price":"239015","month_date_yyyymm":"2020-09-01"},{"county_fips":"48177","median_listing_price":"237000","month_date_yyyymm":"2020-08-01"},{"county_fips":"48177","median_listing_price":"237000","month_date_yyyymm":"2020-07-01"},{"county_fips":"48177","median_listing_price":"237000","month_date_yyyymm":"2020-06-01"},{"county_fips":"48177","median_listing_price":"232500","month_date_yyyymm":"2020-05-01"},{"county_fips":"48177","median_listing_price":"252450","month_date_yyyymm":"2020-04-01"},{"county_fips":"48177","median_listing_price":"269450","month_date_yyyymm":"2020-03-01"},{"county_fips":"48177","median_listing_price":"300000","month_date_yyyymm":"2020-02-01"},{"county_fips":"48177","median_listing_price":"298750","month_date_yyyymm":"2020-01-01"},{"county_fips":"48177","median_listing_price":"298000","month_date_yyyymm":"2019-12-01"},{"county_fips":"48177","median_listing_price":"299000","month_date_yyyymm":"2019-11-01"},{"county_fips":"48177","median_listing_price":"283020","month_date_yyyymm":"2019-10-01"},{"county_fips":"48177","median_listing_price":"275893","month_date_yyyymm":"2019-09-01"},{"county_fips":"48177","median_listing_price":"290027","month_date_yyyymm":"2019-08-01"},{"county_fips":"48177","median_listing_price":"299225","month_date_yyyymm":"2019-07-01"},{"county_fips":"48177","median_listing_price":"285500","month_date_yyyymm":"2019-06-01"},{"county_fips":"48177","median_listing_price":"292225","month_date_yyyymm":"2019-05-01"},{"county_fips":"48177","median_listing_price":"283475","month_date_yyyymm":"2019-04-01"},{"county_fips":"48177","median_listing_price":"238000","month_date_yyyymm":"2019-03-01"}]}