{"county_fips":"48433","county_name":"stonewall, tx","timeseries":[{"county_fips":"48433","median_listing_price":"245000","month_date_yyyymm":"2025-03-01"},{"county_fips":"48433","median_listing_price":"280000","month_date_yyyymm":"2025-02-01"},{"county_fips":"48433","median_listing_price":"252450","month_date_yyyymm":"2025-01-01"},{"county_fips":"48433","median_listing_price":"221175","month_date_yyyymm":"2024-12-01"},{"county_fips":"48433","median_listing_price":"99500","month_date_yyyymm":"2024-11-01"},{"county_fips":"48433","median_listing_price":"99500","month_date_yyyymm":"2024-10-01"},{"county_fips":"48433","median_listing_price":"109700","month_date_yyyymm":"2024-09-01"},{"county_fips":"48433","median_listing_price":"174900","month_date_yyyymm":"2024-08-01"},{"county_fips":"48433","median_listing_price":"164300","month_date_yyyymm":"2024-07-01"},{"county_fips":"48433","median_listing_price":"153700","month_date_yyyymm":"2024-06-01"},{"county_fips":"48433","median_listing_price":"174900","month_date_yyyymm":"2024-05-01"},{"county_fips":"48433","median_listing_price":"174900","month_date_yyyymm":"2024-04-01"},{"county_fips":"48433","median_listing_price":"152200","month_date_yyyymm":"2024-03-01"},{"county_fips":"48433","median_listing_price":"199900","month_date_yyyymm":"2024-02-01"},{"county_fips":"48433","median_listing_price":"199900","month_date_yyyymm":"2024-01-01"},{"county_fips":"48433","median_listing_price":"139900","month_date_yyyymm":"2023-12-01"},{"county_fips":"48433","median_listing_price":"139900","month_date_yyyymm":"2023-11-01"},{"county_fips":"48433","median_listing_price":"139900","month_date_yyyymm":"2023-10-01"},{"county_fips":"48433","median_listing_price":"139900","month_date_yyyymm":"2023-09-01"},{"county_fips":"48433","median_listing_price":"139900","month_date_yyyymm":"2023-08-01"},{"county_fips":"48433","median_listing_price":"139900","month_date_yyyymm":"2023-07-01"},{"county_fips":"48433","median_listing_price":"305950","month_date_yyyymm":"2023-05-01"},{"county_fips":"48433","median_listing_price":"312000","month_date_yyyymm":"2023-04-01"},{"county_fips":"48433","median_listing_price":"312000","month_date_yyyymm":"2023-03-01"},{"county_fips":"48433","median_listing_price":"248250","month_date_yyyymm":"2023-02-01"},{"county_fips":"48433","median_listing_price":"254950","month_date_yyyymm":"2023-01-01"},{"county_fips":"48433","median_listing_price":"189900","month_date_yyyymm":"2022-12-01"},{"county_fips":"48433","median_listing_price":"307450","month_date_yyyymm":"2022-11-01"},{"county_fips":"48433","median_listing_price":"310000","month_date_yyyymm":"2022-10-01"},{"county_fips":"48433","median_listing_price":"222750","month_date_yyyymm":"2022-09-01"},{"county_fips":"48433","median_listing_price":"56975","month_date_yyyymm":"2022-08-01"},{"county_fips":"48433","median_listing_price":"67950","month_date_yyyymm":"2022-07-01"},{"county_fips":"48433","median_listing_price":"97000","month_date_yyyymm":"2022-06-01"},{"county_fips":"48433","median_listing_price":"94950","month_date_yyyymm":"2022-05-01"},{"county_fips":"48433","median_listing_price":"95000","month_date_yyyymm":"2022-04-01"},{"county_fips":"48433","median_listing_price":"95000","month_date_yyyymm":"2022-03-01"},{"county_fips":"48433","median_listing_price":"95000","month_date_yyyymm":"2022-02-01"},{"county_fips":"48433","median_listing_price":"65000","month_date_yyyymm":"2022-01-01"},{"county_fips":"48433","median_listing_price":"227500","month_date_yyyymm":"2021-12-01"},{"county_fips":"48433","median_listing_price":"430000","month_date_yyyymm":"2021-11-01"},{"county_fips":"48433","median_listing_price":"430000","month_date_yyyymm":"2021-10-01"},{"county_fips":"48433","median_listing_price":"338750","month_date_yyyymm":"2021-09-01"},{"county_fips":"48433","median_listing_price":"352450","month_date_yyyymm":"2021-08-01"},{"county_fips":"48433","median_listing_price":"274900","month_date_yyyymm":"2021-07-01"},{"county_fips":"48433","median_listing_price":"207000","month_date_yyyymm":"2021-06-01"},{"county_fips":"48433","median_listing_price":"207000","month_date_yyyymm":"2021-05-01"},{"county_fips":"48433","median_listing_price":"178500","month_date_yyyymm":"2021-04-01"},{"county_fips":"48433","median_listing_price":"194975","month_date_yyyymm":"2021-03-01"},{"county_fips":"48433","median_listing_price":"194975","month_date_yyyymm":"2021-02-01"},{"county_fips":"48433","median_listing_price":"150000","month_date_yyyymm":"2021-01-01"},{"county_fips":"48433","median_listing_price":"138500","month_date_yyyymm":"2020-10-01"},{"county_fips":"48433","median_listing_price":"138500","month_date_yyyymm":"2020-09-01"},{"county_fips":"48433","median_listing_price":"138500","month_date_yyyymm":"2020-08-01"},{"county_fips":"48433","median_listing_price":"22500","month_date_yyyymm":"2020-06-01"},{"county_fips":"48433","median_listing_price":"25000","month_date_yyyymm":"2020-05-01"},{"county_fips":"48433","median_listing_price":"25000","month_date_yyyymm":"2020-04-01"},{"county_fips":"48433","median_listing_price":"25000","month_date_yyyymm":"2020-03-01"},{"county_fips":"48433","median_listing_price":"","month_date_yyyymm":"2019-03-01"}]}