{"county_fips":"53049","county_name":"pacific, wa","timeseries":[{"county_fips":"53049","median_listing_price":"449900","month_date_yyyymm":"2025-03-01"},{"county_fips":"53049","median_listing_price":"424950","month_date_yyyymm":"2025-02-01"},{"county_fips":"53049","median_listing_price":"420475","month_date_yyyymm":"2025-01-01"},{"county_fips":"53049","median_listing_price":"402450","month_date_yyyymm":"2024-12-01"},{"county_fips":"53049","median_listing_price":"405000","month_date_yyyymm":"2024-11-01"},{"county_fips":"53049","median_listing_price":"415125","month_date_yyyymm":"2024-10-01"},{"county_fips":"53049","median_listing_price":"424750","month_date_yyyymm":"2024-09-01"},{"county_fips":"53049","median_listing_price":"425000","month_date_yyyymm":"2024-08-01"},{"county_fips":"53049","median_listing_price":"412450","month_date_yyyymm":"2024-07-01"},{"county_fips":"53049","median_listing_price":"399950","month_date_yyyymm":"2024-06-01"},{"county_fips":"53049","median_listing_price":"410000","month_date_yyyymm":"2024-05-01"},{"county_fips":"53049","median_listing_price":"417000","month_date_yyyymm":"2024-04-01"},{"county_fips":"53049","median_listing_price":"435000","month_date_yyyymm":"2024-03-01"},{"county_fips":"53049","median_listing_price":"424750","month_date_yyyymm":"2024-02-01"},{"county_fips":"53049","median_listing_price":"425000","month_date_yyyymm":"2024-01-01"},{"county_fips":"53049","median_listing_price":"439900","month_date_yyyymm":"2023-12-01"},{"county_fips":"53049","median_listing_price":"432000","month_date_yyyymm":"2023-11-01"},{"county_fips":"53049","median_listing_price":"425000","month_date_yyyymm":"2023-10-01"},{"county_fips":"53049","median_listing_price":"425000","month_date_yyyymm":"2023-09-01"},{"county_fips":"53049","median_listing_price":"425000","month_date_yyyymm":"2023-08-01"},{"county_fips":"53049","median_listing_price":"424500","month_date_yyyymm":"2023-07-01"},{"county_fips":"53049","median_listing_price":"424500","month_date_yyyymm":"2023-06-01"},{"county_fips":"53049","median_listing_price":"434250","month_date_yyyymm":"2023-05-01"},{"county_fips":"53049","median_listing_price":"435000","month_date_yyyymm":"2023-04-01"},{"county_fips":"53049","median_listing_price":"429250","month_date_yyyymm":"2023-03-01"},{"county_fips":"53049","median_listing_price":"432000","month_date_yyyymm":"2023-02-01"},{"county_fips":"53049","median_listing_price":"439500","month_date_yyyymm":"2023-01-01"},{"county_fips":"53049","median_listing_price":"420000","month_date_yyyymm":"2022-12-01"},{"county_fips":"53049","median_listing_price":"394500","month_date_yyyymm":"2022-11-01"},{"county_fips":"53049","median_listing_price":"415000","month_date_yyyymm":"2022-10-01"},{"county_fips":"53049","median_listing_price":"418500","month_date_yyyymm":"2022-09-01"},{"county_fips":"53049","median_listing_price":"440625","month_date_yyyymm":"2022-08-01"},{"county_fips":"53049","median_listing_price":"427500","month_date_yyyymm":"2022-07-01"},{"county_fips":"53049","median_listing_price":"405000","month_date_yyyymm":"2022-06-01"},{"county_fips":"53049","median_listing_price":"401500","month_date_yyyymm":"2022-05-01"},{"county_fips":"53049","median_listing_price":"387000","month_date_yyyymm":"2022-04-01"},{"county_fips":"53049","median_listing_price":"398750","month_date_yyyymm":"2022-03-01"},{"county_fips":"53049","median_listing_price":"360225","month_date_yyyymm":"2022-02-01"},{"county_fips":"53049","median_listing_price":"349000","month_date_yyyymm":"2022-01-01"},{"county_fips":"53049","median_listing_price":"365175","month_date_yyyymm":"2021-12-01"},{"county_fips":"53049","median_listing_price":"358675","month_date_yyyymm":"2021-11-01"},{"county_fips":"53049","median_listing_price":"395000","month_date_yyyymm":"2021-10-01"},{"county_fips":"53049","median_listing_price":"395000","month_date_yyyymm":"2021-09-01"},{"county_fips":"53049","median_listing_price":"404500","month_date_yyyymm":"2021-08-01"},{"county_fips":"53049","median_listing_price":"410000","month_date_yyyymm":"2021-07-01"},{"county_fips":"53049","median_listing_price":"349925","month_date_yyyymm":"2021-06-01"},{"county_fips":"53049","median_listing_price":"380000","month_date_yyyymm":"2021-05-01"},{"county_fips":"53049","median_listing_price":"342000","month_date_yyyymm":"2021-04-01"},{"county_fips":"53049","median_listing_price":"324625","month_date_yyyymm":"2021-03-01"},{"county_fips":"53049","median_listing_price":"275000","month_date_yyyymm":"2021-02-01"},{"county_fips":"53049","median_listing_price":"299450","month_date_yyyymm":"2021-01-01"},{"county_fips":"53049","median_listing_price":"320125","month_date_yyyymm":"2020-12-01"},{"county_fips":"53049","median_listing_price":"302000","month_date_yyyymm":"2020-11-01"},{"county_fips":"53049","median_listing_price":"299000","month_date_yyyymm":"2020-10-01"},{"county_fips":"53049","median_listing_price":"284500","month_date_yyyymm":"2020-09-01"},{"county_fips":"53049","median_listing_price":"279900","month_date_yyyymm":"2020-08-01"},{"county_fips":"53049","median_listing_price":"283124","month_date_yyyymm":"2020-07-01"},{"county_fips":"53049","median_listing_price":"280575","month_date_yyyymm":"2020-06-01"},{"county_fips":"53049","median_listing_price":"280000","month_date_yyyymm":"2020-05-01"},{"county_fips":"53049","median_listing_price":"299500","month_date_yyyymm":"2020-04-01"},{"county_fips":"53049","median_listing_price":"292225","month_date_yyyymm":"2020-03-01"},{"county_fips":"53049","median_listing_price":"285000","month_date_yyyymm":"2020-02-01"},{"county_fips":"53049","median_listing_price":"271225","month_date_yyyymm":"2020-01-01"},{"county_fips":"53049","median_listing_price":"279450","month_date_yyyymm":"2019-12-01"},{"county_fips":"53049","median_listing_price":"262450","month_date_yyyymm":"2019-11-01"},{"county_fips":"53049","median_listing_price":"266117","month_date_yyyymm":"2019-10-01"},{"county_fips":"53049","median_listing_price":"266332","month_date_yyyymm":"2019-09-01"},{"county_fips":"53049","median_listing_price":"268173","month_date_yyyymm":"2019-08-01"},{"county_fips":"53049","median_listing_price":"260325","month_date_yyyymm":"2019-07-01"},{"county_fips":"53049","median_listing_price":"252450","month_date_yyyymm":"2019-06-01"},{"county_fips":"53049","median_listing_price":"257191","month_date_yyyymm":"2019-05-01"},{"county_fips":"53049","median_listing_price":"258553","month_date_yyyymm":"2019-04-01"},{"county_fips":"53049","median_listing_price":"259171","month_date_yyyymm":"2019-03-01"}]}