{"county_fips":"01037","county_name":"coosa, al","timeseries":[{"county_fips":"01037","median_listing_price":"267450","month_date_yyyymm":"2025-03-01"},{"county_fips":"01037","median_listing_price":"269950","month_date_yyyymm":"2025-02-01"},{"county_fips":"01037","median_listing_price":"311725","month_date_yyyymm":"2025-01-01"},{"county_fips":"01037","median_listing_price":"336725","month_date_yyyymm":"2024-12-01"},{"county_fips":"01037","median_listing_price":"334450","month_date_yyyymm":"2024-11-01"},{"county_fips":"01037","median_listing_price":"292000","month_date_yyyymm":"2024-10-01"},{"county_fips":"01037","median_listing_price":"275000","month_date_yyyymm":"2024-09-01"},{"county_fips":"01037","median_listing_price":"275000","month_date_yyyymm":"2024-08-01"},{"county_fips":"01037","median_listing_price":"320000","month_date_yyyymm":"2024-07-01"},{"county_fips":"01037","median_listing_price":"389950","month_date_yyyymm":"2024-06-01"},{"county_fips":"01037","median_listing_price":"399925","month_date_yyyymm":"2024-05-01"},{"county_fips":"01037","median_listing_price":"399450","month_date_yyyymm":"2024-04-01"},{"county_fips":"01037","median_listing_price":"375000","month_date_yyyymm":"2024-03-01"},{"county_fips":"01037","median_listing_price":"297500","month_date_yyyymm":"2024-02-01"},{"county_fips":"01037","median_listing_price":"469000","month_date_yyyymm":"2024-01-01"},{"county_fips":"01037","median_listing_price":"275000","month_date_yyyymm":"2023-12-01"},{"county_fips":"01037","median_listing_price":"242500","month_date_yyyymm":"2023-11-01"},{"county_fips":"01037","median_listing_price":"241250","month_date_yyyymm":"2023-10-01"},{"county_fips":"01037","median_listing_price":"275000","month_date_yyyymm":"2023-09-01"},{"county_fips":"01037","median_listing_price":"297500","month_date_yyyymm":"2023-08-01"},{"county_fips":"01037","median_listing_price":"275000","month_date_yyyymm":"2023-07-01"},{"county_fips":"01037","median_listing_price":"279000","month_date_yyyymm":"2023-06-01"},{"county_fips":"01037","median_listing_price":"381000","month_date_yyyymm":"2023-05-01"},{"county_fips":"01037","median_listing_price":"449950","month_date_yyyymm":"2023-04-01"},{"county_fips":"01037","median_listing_price":"486250","month_date_yyyymm":"2023-03-01"},{"county_fips":"01037","median_listing_price":"438650","month_date_yyyymm":"2023-02-01"},{"county_fips":"01037","median_listing_price":"425124","month_date_yyyymm":"2023-01-01"},{"county_fips":"01037","median_listing_price":"359000","month_date_yyyymm":"2022-12-01"},{"county_fips":"01037","median_listing_price":"349700","month_date_yyyymm":"2022-11-01"},{"county_fips":"01037","median_listing_price":"359000","month_date_yyyymm":"2022-10-01"},{"county_fips":"01037","median_listing_price":"344900","month_date_yyyymm":"2022-09-01"},{"county_fips":"01037","median_listing_price":"365925","month_date_yyyymm":"2022-08-01"},{"county_fips":"01037","median_listing_price":"409000","month_date_yyyymm":"2022-07-01"},{"county_fips":"01037","median_listing_price":"417400","month_date_yyyymm":"2022-06-01"},{"county_fips":"01037","median_listing_price":"436150","month_date_yyyymm":"2022-05-01"},{"county_fips":"01037","median_listing_price":"394000","month_date_yyyymm":"2022-04-01"},{"county_fips":"01037","median_listing_price":"419225","month_date_yyyymm":"2022-03-01"},{"county_fips":"01037","median_listing_price":"453200","month_date_yyyymm":"2022-02-01"},{"county_fips":"01037","median_listing_price":"439450","month_date_yyyymm":"2022-01-01"},{"county_fips":"01037","median_listing_price":"345000","month_date_yyyymm":"2021-12-01"},{"county_fips":"01037","median_listing_price":"348675","month_date_yyyymm":"2021-11-01"},{"county_fips":"01037","median_listing_price":"229000","month_date_yyyymm":"2021-10-01"},{"county_fips":"01037","median_listing_price":"292500","month_date_yyyymm":"2021-09-01"},{"county_fips":"01037","median_listing_price":"316175","month_date_yyyymm":"2021-08-01"},{"county_fips":"01037","median_listing_price":"254600","month_date_yyyymm":"2021-07-01"},{"county_fips":"01037","median_listing_price":"301150","month_date_yyyymm":"2021-06-01"},{"county_fips":"01037","median_listing_price":"299000","month_date_yyyymm":"2021-05-01"},{"county_fips":"01037","median_listing_price":"243225","month_date_yyyymm":"2021-04-01"},{"county_fips":"01037","median_listing_price":"265850","month_date_yyyymm":"2021-03-01"},{"county_fips":"01037","median_listing_price":"302300","month_date_yyyymm":"2021-02-01"},{"county_fips":"01037","median_listing_price":"339700","month_date_yyyymm":"2021-01-01"},{"county_fips":"01037","median_listing_price":"386950","month_date_yyyymm":"2020-12-01"},{"county_fips":"01037","median_listing_price":"362400","month_date_yyyymm":"2020-11-01"},{"county_fips":"01037","median_listing_price":"289900","month_date_yyyymm":"2020-10-01"},{"county_fips":"01037","median_listing_price":"275000","month_date_yyyymm":"2020-09-01"},{"county_fips":"01037","median_listing_price":"254950","month_date_yyyymm":"2020-08-01"},{"county_fips":"01037","median_listing_price":"259675","month_date_yyyymm":"2020-07-01"},{"county_fips":"01037","median_listing_price":"289675","month_date_yyyymm":"2020-06-01"},{"county_fips":"01037","median_listing_price":"332400","month_date_yyyymm":"2020-05-01"},{"county_fips":"01037","median_listing_price":"279450","month_date_yyyymm":"2020-04-01"},{"county_fips":"01037","median_listing_price":"219000","month_date_yyyymm":"2020-03-01"},{"county_fips":"01037","median_listing_price":"210000","month_date_yyyymm":"2020-02-01"},{"county_fips":"01037","median_listing_price":"218125","month_date_yyyymm":"2020-01-01"},{"county_fips":"01037","median_listing_price":"191475","month_date_yyyymm":"2019-12-01"},{"county_fips":"01037","median_listing_price":"199900","month_date_yyyymm":"2019-11-01"},{"county_fips":"01037","median_listing_price":"209023","month_date_yyyymm":"2019-10-01"},{"county_fips":"01037","median_listing_price":"205784","month_date_yyyymm":"2019-09-01"},{"county_fips":"01037","median_listing_price":"219714","month_date_yyyymm":"2019-08-01"},{"county_fips":"01037","median_listing_price":"239000","month_date_yyyymm":"2019-07-01"},{"county_fips":"01037","median_listing_price":"229000","month_date_yyyymm":"2019-06-01"},{"county_fips":"01037","median_listing_price":"282450","month_date_yyyymm":"2019-05-01"},{"county_fips":"01037","median_listing_price":"297214","month_date_yyyymm":"2019-04-01"},{"county_fips":"01037","median_listing_price":"284714","month_date_yyyymm":"2019-03-01"}]}