{"county_fips":"04013","county_name":"maricopa, az","timeseries":[{"county_fips":"04013","median_listing_price":"548000","month_date_yyyymm":"2025-03-01"},{"county_fips":"04013","median_listing_price":"545000","month_date_yyyymm":"2025-02-01"},{"county_fips":"04013","median_listing_price":"540553","month_date_yyyymm":"2025-01-01"},{"county_fips":"04013","median_listing_price":"532400","month_date_yyyymm":"2024-12-01"},{"county_fips":"04013","median_listing_price":"545000","month_date_yyyymm":"2024-11-01"},{"county_fips":"04013","median_listing_price":"549450","month_date_yyyymm":"2024-10-01"},{"county_fips":"04013","median_listing_price":"549950","month_date_yyyymm":"2024-09-01"},{"county_fips":"04013","median_listing_price":"549893","month_date_yyyymm":"2024-08-01"},{"county_fips":"04013","median_listing_price":"557000","month_date_yyyymm":"2024-07-01"},{"county_fips":"04013","median_listing_price":"575000","month_date_yyyymm":"2024-06-01"},{"county_fips":"04013","median_listing_price":"582495","month_date_yyyymm":"2024-05-01"},{"county_fips":"04013","median_listing_price":"577000","month_date_yyyymm":"2024-04-01"},{"county_fips":"04013","median_listing_price":"575000","month_date_yyyymm":"2024-03-01"},{"county_fips":"04013","median_listing_price":"582500","month_date_yyyymm":"2024-02-01"},{"county_fips":"04013","median_listing_price":"575000","month_date_yyyymm":"2024-01-01"},{"county_fips":"04013","median_listing_price":"564000","month_date_yyyymm":"2023-12-01"},{"county_fips":"04013","median_listing_price":"549999","month_date_yyyymm":"2023-11-01"},{"county_fips":"04013","median_listing_price":"564130","month_date_yyyymm":"2023-10-01"},{"county_fips":"04013","median_listing_price":"569990","month_date_yyyymm":"2023-09-01"},{"county_fips":"04013","median_listing_price":"577000","month_date_yyyymm":"2023-08-01"},{"county_fips":"04013","median_listing_price":"575000","month_date_yyyymm":"2023-07-01"},{"county_fips":"04013","median_listing_price":"575000","month_date_yyyymm":"2023-06-01"},{"county_fips":"04013","median_listing_price":"560610","month_date_yyyymm":"2023-05-01"},{"county_fips":"04013","median_listing_price":"549500","month_date_yyyymm":"2023-04-01"},{"county_fips":"04013","median_listing_price":"527000","month_date_yyyymm":"2023-03-01"}]}