{"county_fips":"12089","county_name":"nassau, fl","timeseries":[{"county_fips":"12089","median_listing_price":"625000","month_date_yyyymm":"2025-03-01"},{"county_fips":"12089","median_listing_price":"599900","month_date_yyyymm":"2025-02-01"},{"county_fips":"12089","median_listing_price":"599000","month_date_yyyymm":"2025-01-01"},{"county_fips":"12089","median_listing_price":"600000","month_date_yyyymm":"2024-12-01"},{"county_fips":"12089","median_listing_price":"599900","month_date_yyyymm":"2024-11-01"},{"county_fips":"12089","median_listing_price":"631225","month_date_yyyymm":"2024-10-01"},{"county_fips":"12089","median_listing_price":"633950","month_date_yyyymm":"2024-09-01"},{"county_fips":"12089","median_listing_price":"636450","month_date_yyyymm":"2024-08-01"},{"county_fips":"12089","median_listing_price":"629700","month_date_yyyymm":"2024-07-01"},{"county_fips":"12089","median_listing_price":"596500","month_date_yyyymm":"2024-06-01"},{"county_fips":"12089","median_listing_price":"591675","month_date_yyyymm":"2024-05-01"},{"county_fips":"12089","median_listing_price":"598725","month_date_yyyymm":"2024-04-01"},{"county_fips":"12089","median_listing_price":"592450","month_date_yyyymm":"2024-03-01"},{"county_fips":"12089","median_listing_price":"589950","month_date_yyyymm":"2024-02-01"},{"county_fips":"12089","median_listing_price":"584950","month_date_yyyymm":"2024-01-01"},{"county_fips":"12089","median_listing_price":"595000","month_date_yyyymm":"2023-12-01"},{"county_fips":"12089","median_listing_price":"581450","month_date_yyyymm":"2023-11-01"},{"county_fips":"12089","median_listing_price":"577327","month_date_yyyymm":"2023-10-01"},{"county_fips":"12089","median_listing_price":"584900","month_date_yyyymm":"2023-09-01"},{"county_fips":"12089","median_listing_price":"589961","month_date_yyyymm":"2023-08-01"},{"county_fips":"12089","median_listing_price":"599900","month_date_yyyymm":"2023-07-01"},{"county_fips":"12089","median_listing_price":"599000","month_date_yyyymm":"2023-06-01"},{"county_fips":"12089","median_listing_price":"594950","month_date_yyyymm":"2023-05-01"},{"county_fips":"12089","median_listing_price":"574625","month_date_yyyymm":"2023-04-01"},{"county_fips":"12089","median_listing_price":"557723","month_date_yyyymm":"2023-03-01"},{"county_fips":"12089","median_listing_price":"536725","month_date_yyyymm":"2023-02-01"},{"county_fips":"12089","median_listing_price":"499675","month_date_yyyymm":"2023-01-01"},{"county_fips":"12089","median_listing_price":"499000","month_date_yyyymm":"2022-12-01"},{"county_fips":"12089","median_listing_price":"499900","month_date_yyyymm":"2022-11-01"},{"county_fips":"12089","median_listing_price":"525000","month_date_yyyymm":"2022-10-01"},{"county_fips":"12089","median_listing_price":"499900","month_date_yyyymm":"2022-09-01"},{"county_fips":"12089","median_listing_price":"537000","month_date_yyyymm":"2022-08-01"},{"county_fips":"12089","median_listing_price":"557450","month_date_yyyymm":"2022-07-01"},{"county_fips":"12089","median_listing_price":"595593","month_date_yyyymm":"2022-06-01"},{"county_fips":"12089","median_listing_price":"589450","month_date_yyyymm":"2022-05-01"},{"county_fips":"12089","median_listing_price":"584900","month_date_yyyymm":"2022-04-01"},{"county_fips":"12089","median_listing_price":"534450","month_date_yyyymm":"2022-03-01"},{"county_fips":"12089","median_listing_price":"532764","month_date_yyyymm":"2022-02-01"},{"county_fips":"12089","median_listing_price":"504999","month_date_yyyymm":"2022-01-01"},{"county_fips":"12089","median_listing_price":"516950","month_date_yyyymm":"2021-12-01"},{"county_fips":"12089","median_listing_price":"509300","month_date_yyyymm":"2021-11-01"},{"county_fips":"12089","median_listing_price":"499000","month_date_yyyymm":"2021-10-01"},{"county_fips":"12089","median_listing_price":"498750","month_date_yyyymm":"2021-09-01"},{"county_fips":"12089","median_listing_price":"499450","month_date_yyyymm":"2021-08-01"},{"county_fips":"12089","median_listing_price":"478966","month_date_yyyymm":"2021-07-01"},{"county_fips":"12089","median_listing_price":"504500","month_date_yyyymm":"2021-06-01"},{"county_fips":"12089","median_listing_price":"537500","month_date_yyyymm":"2021-05-01"},{"county_fips":"12089","median_listing_price":"549675","month_date_yyyymm":"2021-04-01"},{"county_fips":"12089","median_listing_price":"525000","month_date_yyyymm":"2021-03-01"},{"county_fips":"12089","median_listing_price":"497225","month_date_yyyymm":"2021-02-01"},{"county_fips":"12089","median_listing_price":"448500","month_date_yyyymm":"2021-01-01"},{"county_fips":"12089","median_listing_price":"393950","month_date_yyyymm":"2020-12-01"},{"county_fips":"12089","median_listing_price":"414500","month_date_yyyymm":"2020-11-01"},{"county_fips":"12089","median_listing_price":"422450","month_date_yyyymm":"2020-10-01"},{"county_fips":"12089","median_listing_price":"417450","month_date_yyyymm":"2020-09-01"},{"county_fips":"12089","median_listing_price":"396750","month_date_yyyymm":"2020-08-01"},{"county_fips":"12089","median_listing_price":"380500","month_date_yyyymm":"2020-07-01"},{"county_fips":"12089","median_listing_price":"396950","month_date_yyyymm":"2020-06-01"},{"county_fips":"12089","median_listing_price":"405945","month_date_yyyymm":"2020-05-01"},{"county_fips":"12089","median_listing_price":"394975","month_date_yyyymm":"2020-04-01"},{"county_fips":"12089","median_listing_price":"395011","month_date_yyyymm":"2020-03-01"},{"county_fips":"12089","median_listing_price":"387500","month_date_yyyymm":"2020-02-01"},{"county_fips":"12089","median_listing_price":"384951","month_date_yyyymm":"2020-01-01"},{"county_fips":"12089","median_listing_price":"387825","month_date_yyyymm":"2019-12-01"},{"county_fips":"12089","median_listing_price":"389000","month_date_yyyymm":"2019-11-01"},{"county_fips":"12089","median_listing_price":"380090","month_date_yyyymm":"2019-10-01"},{"county_fips":"12089","median_listing_price":"380633","month_date_yyyymm":"2019-09-01"},{"county_fips":"12089","median_listing_price":"381447","month_date_yyyymm":"2019-08-01"},{"county_fips":"12089","median_listing_price":"381370","month_date_yyyymm":"2019-07-01"},{"county_fips":"12089","median_listing_price":"390995","month_date_yyyymm":"2019-06-01"},{"county_fips":"12089","median_listing_price":"389096","month_date_yyyymm":"2019-05-01"},{"county_fips":"12089","median_listing_price":"380845","month_date_yyyymm":"2019-04-01"},{"county_fips":"12089","median_listing_price":"373586","month_date_yyyymm":"2019-03-01"}]}