{"county_fips":"17175","county_name":"stark, il","timeseries":[{"county_fips":"17175","median_listing_price":"144900","month_date_yyyymm":"2025-03-01"},{"county_fips":"17175","median_listing_price":"90000","month_date_yyyymm":"2025-02-01"},{"county_fips":"17175","median_listing_price":"113125","month_date_yyyymm":"2025-01-01"},{"county_fips":"17175","median_listing_price":"135000","month_date_yyyymm":"2024-12-01"},{"county_fips":"17175","median_listing_price":"111450","month_date_yyyymm":"2024-11-01"},{"county_fips":"17175","median_listing_price":"155700","month_date_yyyymm":"2024-10-01"},{"county_fips":"17175","median_listing_price":"159900","month_date_yyyymm":"2024-09-01"},{"county_fips":"17175","median_listing_price":"190650","month_date_yyyymm":"2024-08-01"},{"county_fips":"17175","median_listing_price":"220650","month_date_yyyymm":"2024-07-01"},{"county_fips":"17175","median_listing_price":"154000","month_date_yyyymm":"2024-06-01"},{"county_fips":"17175","median_listing_price":"168725","month_date_yyyymm":"2024-05-01"},{"county_fips":"17175","median_listing_price":"153700","month_date_yyyymm":"2024-04-01"},{"county_fips":"17175","median_listing_price":"107500","month_date_yyyymm":"2024-03-01"},{"county_fips":"17175","median_listing_price":"118075","month_date_yyyymm":"2024-02-01"},{"county_fips":"17175","median_listing_price":"114975","month_date_yyyymm":"2024-01-01"},{"county_fips":"17175","median_listing_price":"125000","month_date_yyyymm":"2023-12-01"},{"county_fips":"17175","median_listing_price":"100000","month_date_yyyymm":"2023-11-01"},{"county_fips":"17175","median_listing_price":"105000","month_date_yyyymm":"2023-10-01"},{"county_fips":"17175","median_listing_price":"125000","month_date_yyyymm":"2023-09-01"},{"county_fips":"17175","median_listing_price":"116725","month_date_yyyymm":"2023-08-01"},{"county_fips":"17175","median_listing_price":"219900","month_date_yyyymm":"2023-07-01"},{"county_fips":"17175","median_listing_price":"163450","month_date_yyyymm":"2023-06-01"},{"county_fips":"17175","median_listing_price":"156200","month_date_yyyymm":"2023-05-01"},{"county_fips":"17175","median_listing_price":"211950","month_date_yyyymm":"2023-04-01"},{"county_fips":"17175","median_listing_price":"261709","month_date_yyyymm":"2023-03-01"},{"county_fips":"17175","median_listing_price":"103917","month_date_yyyymm":"2023-02-01"},{"county_fips":"17175","median_listing_price":"97913","month_date_yyyymm":"2023-01-01"},{"county_fips":"17175","median_listing_price":"119900","month_date_yyyymm":"2022-12-01"},{"county_fips":"17175","median_listing_price":"119654","month_date_yyyymm":"2022-11-01"},{"county_fips":"17175","median_listing_price":"114409","month_date_yyyymm":"2022-10-01"},{"county_fips":"17175","median_listing_price":"139225","month_date_yyyymm":"2022-09-01"},{"county_fips":"17175","median_listing_price":"144225","month_date_yyyymm":"2022-08-01"},{"county_fips":"17175","median_listing_price":"149000","month_date_yyyymm":"2022-07-01"},{"county_fips":"17175","median_listing_price":"122250","month_date_yyyymm":"2022-06-01"},{"county_fips":"17175","median_listing_price":"127175","month_date_yyyymm":"2022-05-01"},{"county_fips":"17175","median_listing_price":"127500","month_date_yyyymm":"2022-04-01"},{"county_fips":"17175","median_listing_price":"96175","month_date_yyyymm":"2022-03-01"},{"county_fips":"17175","median_listing_price":"69900","month_date_yyyymm":"2022-02-01"},{"county_fips":"17175","median_listing_price":"154900","month_date_yyyymm":"2022-01-01"},{"county_fips":"17175","median_listing_price":"69900","month_date_yyyymm":"2021-12-01"},{"county_fips":"17175","median_listing_price":"78700","month_date_yyyymm":"2021-11-01"},{"county_fips":"17175","median_listing_price":"82400","month_date_yyyymm":"2021-10-01"},{"county_fips":"17175","median_listing_price":"77850","month_date_yyyymm":"2021-09-01"},{"county_fips":"17175","median_listing_price":"92450","month_date_yyyymm":"2021-08-01"},{"county_fips":"17175","median_listing_price":"87450","month_date_yyyymm":"2021-07-01"},{"county_fips":"17175","median_listing_price":"85250","month_date_yyyymm":"2021-06-01"},{"county_fips":"17175","median_listing_price":"86500","month_date_yyyymm":"2021-05-01"},{"county_fips":"17175","median_listing_price":"74000","month_date_yyyymm":"2021-04-01"},{"county_fips":"17175","median_listing_price":"75450","month_date_yyyymm":"2021-03-01"},{"county_fips":"17175","median_listing_price":"72650","month_date_yyyymm":"2021-02-01"},{"county_fips":"17175","median_listing_price":"69900","month_date_yyyymm":"2021-01-01"},{"county_fips":"17175","median_listing_price":"75650","month_date_yyyymm":"2020-12-01"},{"county_fips":"17175","median_listing_price":"81700","month_date_yyyymm":"2020-11-01"},{"county_fips":"17175","median_listing_price":"81700","month_date_yyyymm":"2020-10-01"},{"county_fips":"17175","median_listing_price":"77400","month_date_yyyymm":"2020-09-01"},{"county_fips":"17175","median_listing_price":"83900","month_date_yyyymm":"2020-08-01"},{"county_fips":"17175","median_listing_price":"87850","month_date_yyyymm":"2020-07-01"},{"county_fips":"17175","median_listing_price":"82900","month_date_yyyymm":"2020-06-01"},{"county_fips":"17175","median_listing_price":"69178","month_date_yyyymm":"2020-05-01"},{"county_fips":"17175","median_listing_price":"79900","month_date_yyyymm":"2020-04-01"},{"county_fips":"17175","median_listing_price":"83400","month_date_yyyymm":"2020-03-01"},{"county_fips":"17175","median_listing_price":"73950","month_date_yyyymm":"2020-02-01"},{"county_fips":"17175","median_listing_price":"76575","month_date_yyyymm":"2020-01-01"},{"county_fips":"17175","median_listing_price":"79900","month_date_yyyymm":"2019-12-01"},{"county_fips":"17175","median_listing_price":"79200","month_date_yyyymm":"2019-11-01"},{"county_fips":"17175","median_listing_price":"81350","month_date_yyyymm":"2019-10-01"},{"county_fips":"17175","median_listing_price":"87159","month_date_yyyymm":"2019-09-01"},{"county_fips":"17175","median_listing_price":"91864","month_date_yyyymm":"2019-08-01"},{"county_fips":"17175","median_listing_price":"85225","month_date_yyyymm":"2019-07-01"},{"county_fips":"17175","median_listing_price":"64450","month_date_yyyymm":"2019-06-01"},{"county_fips":"17175","median_listing_price":"78000","month_date_yyyymm":"2019-05-01"},{"county_fips":"17175","median_listing_price":"82679","month_date_yyyymm":"2019-04-01"},{"county_fips":"17175","median_listing_price":"77429","month_date_yyyymm":"2019-03-01"}]}