{"county_fips":"19023","county_name":"butler, ia","timeseries":[{"county_fips":"19023","median_listing_price":"199900","month_date_yyyymm":"2025-03-01"},{"county_fips":"19023","median_listing_price":"182125","month_date_yyyymm":"2025-02-01"},{"county_fips":"19023","median_listing_price":"179500","month_date_yyyymm":"2025-01-01"},{"county_fips":"19023","median_listing_price":"196000","month_date_yyyymm":"2024-12-01"},{"county_fips":"19023","median_listing_price":"205000","month_date_yyyymm":"2024-11-01"},{"county_fips":"19023","median_listing_price":"219900","month_date_yyyymm":"2024-10-01"},{"county_fips":"19023","median_listing_price":"210925","month_date_yyyymm":"2024-09-01"},{"county_fips":"19023","median_listing_price":"192200","month_date_yyyymm":"2024-08-01"},{"county_fips":"19023","median_listing_price":"227475","month_date_yyyymm":"2024-07-01"},{"county_fips":"19023","median_listing_price":"177400","month_date_yyyymm":"2024-06-01"},{"county_fips":"19023","median_listing_price":"201200","month_date_yyyymm":"2024-05-01"},{"county_fips":"19023","median_listing_price":"180000","month_date_yyyymm":"2024-04-01"},{"county_fips":"19023","median_listing_price":"177450","month_date_yyyymm":"2024-03-01"},{"county_fips":"19023","median_listing_price":"178475","month_date_yyyymm":"2024-02-01"},{"county_fips":"19023","median_listing_price":"163650","month_date_yyyymm":"2024-01-01"},{"county_fips":"19023","median_listing_price":"160200","month_date_yyyymm":"2023-12-01"},{"county_fips":"19023","median_listing_price":"163200","month_date_yyyymm":"2023-11-01"},{"county_fips":"19023","median_listing_price":"177650","month_date_yyyymm":"2023-10-01"},{"county_fips":"19023","median_listing_price":"194900","month_date_yyyymm":"2023-09-01"},{"county_fips":"19023","median_listing_price":"205925","month_date_yyyymm":"2023-08-01"},{"county_fips":"19023","median_listing_price":"209700","month_date_yyyymm":"2023-07-01"},{"county_fips":"19023","median_listing_price":"233725","month_date_yyyymm":"2023-06-01"},{"county_fips":"19023","median_listing_price":"209975","month_date_yyyymm":"2023-05-01"},{"county_fips":"19023","median_listing_price":"220000","month_date_yyyymm":"2023-04-01"},{"county_fips":"19023","median_listing_price":"296000","month_date_yyyymm":"2023-03-01"},{"county_fips":"19023","median_listing_price":"260200","month_date_yyyymm":"2023-02-01"},{"county_fips":"19023","median_listing_price":"268925","month_date_yyyymm":"2023-01-01"},{"county_fips":"19023","median_listing_price":"242450","month_date_yyyymm":"2022-12-01"},{"county_fips":"19023","median_listing_price":"188425","month_date_yyyymm":"2022-11-01"},{"county_fips":"19023","median_listing_price":"217500","month_date_yyyymm":"2022-10-01"},{"county_fips":"19023","median_listing_price":"227000","month_date_yyyymm":"2022-09-01"},{"county_fips":"19023","median_listing_price":"231625","month_date_yyyymm":"2022-08-01"},{"county_fips":"19023","median_listing_price":"199900","month_date_yyyymm":"2022-07-01"},{"county_fips":"19023","median_listing_price":"182975","month_date_yyyymm":"2022-06-01"},{"county_fips":"19023","median_listing_price":"184500","month_date_yyyymm":"2022-05-01"},{"county_fips":"19023","median_listing_price":"158500","month_date_yyyymm":"2022-04-01"},{"county_fips":"19023","median_listing_price":"157400","month_date_yyyymm":"2022-03-01"},{"county_fips":"19023","median_listing_price":"154975","month_date_yyyymm":"2022-02-01"},{"county_fips":"19023","median_listing_price":"131250","month_date_yyyymm":"2022-01-01"},{"county_fips":"19023","median_listing_price":"134950","month_date_yyyymm":"2021-12-01"},{"county_fips":"19023","median_listing_price":"178550","month_date_yyyymm":"2021-11-01"},{"county_fips":"19023","median_listing_price":"189500","month_date_yyyymm":"2021-10-01"},{"county_fips":"19023","median_listing_price":"175000","month_date_yyyymm":"2021-09-01"},{"county_fips":"19023","median_listing_price":"173550","month_date_yyyymm":"2021-08-01"},{"county_fips":"19023","median_listing_price":"118000","month_date_yyyymm":"2021-07-01"},{"county_fips":"19023","median_listing_price":"91925","month_date_yyyymm":"2021-06-01"},{"county_fips":"19023","median_listing_price":"104500","month_date_yyyymm":"2021-05-01"},{"county_fips":"19023","median_listing_price":"118000","month_date_yyyymm":"2021-04-01"},{"county_fips":"19023","median_listing_price":"119425","month_date_yyyymm":"2021-03-01"},{"county_fips":"19023","median_listing_price":"119425","month_date_yyyymm":"2021-02-01"},{"county_fips":"19023","median_listing_price":"119900","month_date_yyyymm":"2021-01-01"},{"county_fips":"19023","median_listing_price":"119425","month_date_yyyymm":"2020-12-01"},{"county_fips":"19023","median_listing_price":"120850","month_date_yyyymm":"2020-11-01"},{"county_fips":"19023","median_listing_price":"151750","month_date_yyyymm":"2020-10-01"},{"county_fips":"19023","median_listing_price":"128550","month_date_yyyymm":"2020-09-01"},{"county_fips":"19023","median_listing_price":"122200","month_date_yyyymm":"2020-08-01"},{"county_fips":"19023","median_listing_price":"123650","month_date_yyyymm":"2020-07-01"},{"county_fips":"19023","median_listing_price":"133450","month_date_yyyymm":"2020-06-01"},{"county_fips":"19023","median_listing_price":"116450","month_date_yyyymm":"2020-05-01"},{"county_fips":"19023","median_listing_price":"112575","month_date_yyyymm":"2020-04-01"},{"county_fips":"19023","median_listing_price":"112400","month_date_yyyymm":"2020-03-01"},{"county_fips":"19023","median_listing_price":"114900","month_date_yyyymm":"2020-02-01"},{"county_fips":"19023","median_listing_price":"117375","month_date_yyyymm":"2020-01-01"},{"county_fips":"19023","median_listing_price":"121850","month_date_yyyymm":"2019-12-01"},{"county_fips":"19023","median_listing_price":"121200","month_date_yyyymm":"2019-11-01"},{"county_fips":"19023","median_listing_price":"124225","month_date_yyyymm":"2019-10-01"},{"county_fips":"19023","median_listing_price":"127775","month_date_yyyymm":"2019-09-01"},{"county_fips":"19023","median_listing_price":"132050","month_date_yyyymm":"2019-08-01"},{"county_fips":"19023","median_listing_price":"139900","month_date_yyyymm":"2019-07-01"},{"county_fips":"19023","median_listing_price":"124450","month_date_yyyymm":"2019-06-01"},{"county_fips":"19023","median_listing_price":"113725","month_date_yyyymm":"2019-05-01"},{"county_fips":"19023","median_listing_price":"114050","month_date_yyyymm":"2019-04-01"},{"county_fips":"19023","median_listing_price":"113800","month_date_yyyymm":"2019-03-01"}]}