{"county_fips":"46119","county_name":"sully, sd","timeseries":[{"county_fips":"46119","median_listing_price":"299500","month_date_yyyymm":"2025-03-01"},{"county_fips":"46119","median_listing_price":"299500","month_date_yyyymm":"2025-02-01"},{"county_fips":"46119","median_listing_price":"299500","month_date_yyyymm":"2025-01-01"},{"county_fips":"46119","median_listing_price":"302250","month_date_yyyymm":"2024-12-01"},{"county_fips":"46119","median_listing_price":"852500","month_date_yyyymm":"2024-11-01"},{"county_fips":"46119","median_listing_price":"305000","month_date_yyyymm":"2024-10-01"},{"county_fips":"46119","median_listing_price":"305000","month_date_yyyymm":"2024-09-01"},{"county_fips":"46119","median_listing_price":"232500","month_date_yyyymm":"2024-08-01"},{"county_fips":"46119","median_listing_price":"232500","month_date_yyyymm":"2024-07-01"},{"county_fips":"46119","median_listing_price":"296000","month_date_yyyymm":"2024-06-01"},{"county_fips":"46119","median_listing_price":"323750","month_date_yyyymm":"2024-05-01"},{"county_fips":"46119","median_listing_price":"369000","month_date_yyyymm":"2024-04-01"},{"county_fips":"46119","median_listing_price":"499999","month_date_yyyymm":"2024-03-01"},{"county_fips":"46119","median_listing_price":"472499","month_date_yyyymm":"2024-02-01"},{"county_fips":"46119","median_listing_price":"445000","month_date_yyyymm":"2024-01-01"},{"county_fips":"46119","median_listing_price":"399500","month_date_yyyymm":"2023-12-01"},{"county_fips":"46119","median_listing_price":"299000","month_date_yyyymm":"2023-11-01"},{"county_fips":"46119","median_listing_price":"269250","month_date_yyyymm":"2023-10-01"},{"county_fips":"46119","median_listing_price":"269250","month_date_yyyymm":"2023-09-01"},{"county_fips":"46119","median_listing_price":"355500","month_date_yyyymm":"2023-08-01"},{"county_fips":"46119","median_listing_price":"294000","month_date_yyyymm":"2023-07-01"},{"county_fips":"46119","median_listing_price":"299000","month_date_yyyymm":"2023-06-01"},{"county_fips":"46119","median_listing_price":"220125","month_date_yyyymm":"2023-05-01"},{"county_fips":"46119","median_listing_price":"286250","month_date_yyyymm":"2023-04-01"},{"county_fips":"46119","median_listing_price":"298125","month_date_yyyymm":"2023-03-01"},{"county_fips":"46119","median_listing_price":"189000","month_date_yyyymm":"2022-12-01"},{"county_fips":"46119","median_listing_price":"189000","month_date_yyyymm":"2022-11-01"},{"county_fips":"46119","median_listing_price":"292025","month_date_yyyymm":"2022-10-01"},{"county_fips":"46119","median_listing_price":"317025","month_date_yyyymm":"2022-09-01"},{"county_fips":"46119","median_listing_price":"395050","month_date_yyyymm":"2022-08-01"},{"county_fips":"46119","median_listing_price":"216450","month_date_yyyymm":"2022-07-01"},{"county_fips":"46119","median_listing_price":"246625","month_date_yyyymm":"2022-06-01"},{"county_fips":"46119","median_listing_price":"254625","month_date_yyyymm":"2022-05-01"},{"county_fips":"46119","median_listing_price":"187250","month_date_yyyymm":"2022-04-01"},{"county_fips":"46119","median_listing_price":"431250","month_date_yyyymm":"2022-03-01"},{"county_fips":"46119","median_listing_price":"364500","month_date_yyyymm":"2022-02-01"},{"county_fips":"46119","median_listing_price":"264000","month_date_yyyymm":"2022-01-01"},{"county_fips":"46119","median_listing_price":"208500","month_date_yyyymm":"2021-12-01"},{"county_fips":"46119","median_listing_price":"365475","month_date_yyyymm":"2021-11-01"},{"county_fips":"46119","median_listing_price":"209500","month_date_yyyymm":"2021-10-01"},{"county_fips":"46119","median_listing_price":"157500","month_date_yyyymm":"2021-09-01"},{"county_fips":"46119","median_listing_price":"214000","month_date_yyyymm":"2021-08-01"},{"county_fips":"46119","median_listing_price":"114450","month_date_yyyymm":"2021-07-01"},{"county_fips":"46119","median_listing_price":"154450","month_date_yyyymm":"2021-06-01"},{"county_fips":"46119","median_listing_price":"159000","month_date_yyyymm":"2021-05-01"},{"county_fips":"46119","median_listing_price":"206000","month_date_yyyymm":"2021-04-01"},{"county_fips":"46119","median_listing_price":"215000","month_date_yyyymm":"2021-03-01"},{"county_fips":"46119","median_listing_price":"217500","month_date_yyyymm":"2021-02-01"},{"county_fips":"46119","median_listing_price":"225000","month_date_yyyymm":"2021-01-01"},{"county_fips":"46119","median_listing_price":"225000","month_date_yyyymm":"2020-12-01"},{"county_fips":"46119","median_listing_price":"220000","month_date_yyyymm":"2020-11-01"},{"county_fips":"46119","median_listing_price":"225000","month_date_yyyymm":"2020-10-01"},{"county_fips":"46119","median_listing_price":"209950","month_date_yyyymm":"2020-09-01"},{"county_fips":"46119","median_listing_price":"179900","month_date_yyyymm":"2020-08-01"},{"county_fips":"46119","median_listing_price":"179900","month_date_yyyymm":"2020-07-01"},{"county_fips":"46119","median_listing_price":"227450","month_date_yyyymm":"2020-06-01"},{"county_fips":"46119","median_listing_price":"227450","month_date_yyyymm":"2020-05-01"},{"county_fips":"46119","median_listing_price":"252450","month_date_yyyymm":"2020-04-01"},{"county_fips":"46119","median_listing_price":"179900","month_date_yyyymm":"2020-03-01"},{"county_fips":"46119","median_listing_price":"234950","month_date_yyyymm":"2020-02-01"},{"county_fips":"46119","median_listing_price":"299000","month_date_yyyymm":"2020-01-01"},{"county_fips":"46119","median_listing_price":"322000","month_date_yyyymm":"2019-12-01"},{"county_fips":"46119","median_listing_price":"322000","month_date_yyyymm":"2019-11-01"},{"county_fips":"46119","median_listing_price":"225000","month_date_yyyymm":"2019-10-01"},{"county_fips":"46119","median_listing_price":"257614","month_date_yyyymm":"2019-09-01"},{"county_fips":"46119","median_listing_price":"299545","month_date_yyyymm":"2019-08-01"},{"county_fips":"46119","median_listing_price":"312500","month_date_yyyymm":"2019-07-01"},{"county_fips":"46119","median_listing_price":"229000","month_date_yyyymm":"2019-06-01"},{"county_fips":"46119","median_listing_price":"229000","month_date_yyyymm":"2019-05-01"},{"county_fips":"46119","median_listing_price":"205000","month_date_yyyymm":"2019-04-01"},{"county_fips":"46119","median_listing_price":"205000","month_date_yyyymm":"2019-03-01"}]}