{"county_fips":"47073","county_name":"hawkins, tn","timeseries":[{"county_fips":"47073","median_listing_price":"315000","month_date_yyyymm":"2025-03-01"},{"county_fips":"47073","median_listing_price":"304450","month_date_yyyymm":"2025-02-01"},{"county_fips":"47073","median_listing_price":"299972","month_date_yyyymm":"2025-01-01"},{"county_fips":"47073","median_listing_price":"299947","month_date_yyyymm":"2024-12-01"},{"county_fips":"47073","median_listing_price":"325000","month_date_yyyymm":"2024-11-01"},{"county_fips":"47073","median_listing_price":"314600","month_date_yyyymm":"2024-10-01"},{"county_fips":"47073","median_listing_price":"310500","month_date_yyyymm":"2024-09-01"},{"county_fips":"47073","median_listing_price":"324900","month_date_yyyymm":"2024-08-01"},{"county_fips":"47073","median_listing_price":"349225","month_date_yyyymm":"2024-07-01"},{"county_fips":"47073","median_listing_price":"330000","month_date_yyyymm":"2024-06-01"},{"county_fips":"47073","median_listing_price":"330100","month_date_yyyymm":"2024-05-01"},{"county_fips":"47073","median_listing_price":"308650","month_date_yyyymm":"2024-04-01"},{"county_fips":"47073","median_listing_price":"292075","month_date_yyyymm":"2024-03-01"},{"county_fips":"47073","median_listing_price":"297400","month_date_yyyymm":"2024-02-01"},{"county_fips":"47073","median_listing_price":"278743","month_date_yyyymm":"2024-01-01"},{"county_fips":"47073","median_listing_price":"284995","month_date_yyyymm":"2023-12-01"},{"county_fips":"47073","median_listing_price":"284950","month_date_yyyymm":"2023-11-01"},{"county_fips":"47073","median_listing_price":"299900","month_date_yyyymm":"2023-10-01"},{"county_fips":"47073","median_listing_price":"294900","month_date_yyyymm":"2023-09-01"},{"county_fips":"47073","median_listing_price":"302175","month_date_yyyymm":"2023-08-01"},{"county_fips":"47073","median_listing_price":"285000","month_date_yyyymm":"2023-07-01"},{"county_fips":"47073","median_listing_price":"299450","month_date_yyyymm":"2023-06-01"},{"county_fips":"47073","median_listing_price":"319325","month_date_yyyymm":"2023-05-01"},{"county_fips":"47073","median_listing_price":"297000","month_date_yyyymm":"2023-04-01"},{"county_fips":"47073","median_listing_price":"283625","month_date_yyyymm":"2023-03-01"},{"county_fips":"47073","median_listing_price":"289989","month_date_yyyymm":"2023-02-01"},{"county_fips":"47073","median_listing_price":"301113","month_date_yyyymm":"2023-01-01"},{"county_fips":"47073","median_listing_price":"298900","month_date_yyyymm":"2022-12-01"},{"county_fips":"47073","median_listing_price":"286750","month_date_yyyymm":"2022-11-01"},{"county_fips":"47073","median_listing_price":"325000","month_date_yyyymm":"2022-10-01"},{"county_fips":"47073","median_listing_price":"344200","month_date_yyyymm":"2022-09-01"},{"county_fips":"47073","median_listing_price":"322475","month_date_yyyymm":"2022-08-01"},{"county_fips":"47073","median_listing_price":"298748","month_date_yyyymm":"2022-07-01"},{"county_fips":"47073","median_listing_price":"284700","month_date_yyyymm":"2022-06-01"},{"county_fips":"47073","median_listing_price":"277675","month_date_yyyymm":"2022-05-01"},{"county_fips":"47073","median_listing_price":"279900","month_date_yyyymm":"2022-04-01"},{"county_fips":"47073","median_listing_price":"269000","month_date_yyyymm":"2022-03-01"},{"county_fips":"47073","median_listing_price":"266500","month_date_yyyymm":"2022-02-01"},{"county_fips":"47073","median_listing_price":"269000","month_date_yyyymm":"2022-01-01"},{"county_fips":"47073","median_listing_price":"282250","month_date_yyyymm":"2021-12-01"},{"county_fips":"47073","median_listing_price":"269650","month_date_yyyymm":"2021-11-01"},{"county_fips":"47073","median_listing_price":"283700","month_date_yyyymm":"2021-10-01"},{"county_fips":"47073","median_listing_price":"249900","month_date_yyyymm":"2021-09-01"},{"county_fips":"47073","median_listing_price":"275000","month_date_yyyymm":"2021-08-01"},{"county_fips":"47073","median_listing_price":"237500","month_date_yyyymm":"2021-07-01"},{"county_fips":"47073","median_listing_price":"242200","month_date_yyyymm":"2021-06-01"},{"county_fips":"47073","median_listing_price":"247450","month_date_yyyymm":"2021-05-01"},{"county_fips":"47073","median_listing_price":"237225","month_date_yyyymm":"2021-04-01"},{"county_fips":"47073","median_listing_price":"254450","month_date_yyyymm":"2021-03-01"},{"county_fips":"47073","median_listing_price":"226225","month_date_yyyymm":"2021-02-01"},{"county_fips":"47073","median_listing_price":"199900","month_date_yyyymm":"2021-01-01"},{"county_fips":"47073","median_listing_price":"212925","month_date_yyyymm":"2020-12-01"},{"county_fips":"47073","median_listing_price":"229900","month_date_yyyymm":"2020-11-01"},{"county_fips":"47073","median_listing_price":"232900","month_date_yyyymm":"2020-10-01"},{"county_fips":"47073","median_listing_price":"239990","month_date_yyyymm":"2020-09-01"},{"county_fips":"47073","median_listing_price":"239960","month_date_yyyymm":"2020-08-01"},{"county_fips":"47073","median_listing_price":"233800","month_date_yyyymm":"2020-07-01"},{"county_fips":"47073","median_listing_price":"216312","month_date_yyyymm":"2020-06-01"},{"county_fips":"47073","median_listing_price":"219250","month_date_yyyymm":"2020-05-01"},{"county_fips":"47073","median_listing_price":"198250","month_date_yyyymm":"2020-04-01"},{"county_fips":"47073","median_listing_price":"199925","month_date_yyyymm":"2020-03-01"},{"county_fips":"47073","median_listing_price":"197000","month_date_yyyymm":"2020-02-01"},{"county_fips":"47073","median_listing_price":"189650","month_date_yyyymm":"2020-01-01"},{"county_fips":"47073","median_listing_price":"188200","month_date_yyyymm":"2019-12-01"},{"county_fips":"47073","median_listing_price":"186250","month_date_yyyymm":"2019-11-01"},{"county_fips":"47073","median_listing_price":"195520","month_date_yyyymm":"2019-10-01"},{"county_fips":"47073","median_listing_price":"195018","month_date_yyyymm":"2019-09-01"},{"county_fips":"47073","median_listing_price":"193177","month_date_yyyymm":"2019-08-01"},{"county_fips":"47073","median_listing_price":"182220","month_date_yyyymm":"2019-07-01"},{"county_fips":"47073","median_listing_price":"176500","month_date_yyyymm":"2019-06-01"},{"county_fips":"47073","median_listing_price":"172450","month_date_yyyymm":"2019-05-01"},{"county_fips":"47073","median_listing_price":"172700","month_date_yyyymm":"2019-04-01"},{"county_fips":"47073","median_listing_price":"160529","month_date_yyyymm":"2019-03-01"}]}