{"county_fips":"47097","county_name":"lauderdale, tn","timeseries":[{"county_fips":"47097","median_listing_price":"225750","month_date_yyyymm":"2025-03-01"},{"county_fips":"47097","median_listing_price":"195300","month_date_yyyymm":"2025-02-01"},{"county_fips":"47097","median_listing_price":"191500","month_date_yyyymm":"2025-01-01"},{"county_fips":"47097","median_listing_price":"199900","month_date_yyyymm":"2024-12-01"},{"county_fips":"47097","median_listing_price":"199900","month_date_yyyymm":"2024-11-01"},{"county_fips":"47097","median_listing_price":"186725","month_date_yyyymm":"2024-10-01"},{"county_fips":"47097","median_listing_price":"186100","month_date_yyyymm":"2024-09-01"},{"county_fips":"47097","median_listing_price":"178000","month_date_yyyymm":"2024-08-01"},{"county_fips":"47097","median_listing_price":"186500","month_date_yyyymm":"2024-07-01"},{"county_fips":"47097","median_listing_price":"169950","month_date_yyyymm":"2024-06-01"},{"county_fips":"47097","median_listing_price":"161225","month_date_yyyymm":"2024-05-01"},{"county_fips":"47097","median_listing_price":"163750","month_date_yyyymm":"2024-04-01"},{"county_fips":"47097","median_listing_price":"179500","month_date_yyyymm":"2024-03-01"},{"county_fips":"47097","median_listing_price":"174500","month_date_yyyymm":"2024-02-01"},{"county_fips":"47097","median_listing_price":"206500","month_date_yyyymm":"2024-01-01"},{"county_fips":"47097","median_listing_price":"215000","month_date_yyyymm":"2023-12-01"},{"county_fips":"47097","median_listing_price":"176000","month_date_yyyymm":"2023-11-01"},{"county_fips":"47097","median_listing_price":"199950","month_date_yyyymm":"2023-10-01"},{"county_fips":"47097","median_listing_price":"179900","month_date_yyyymm":"2023-09-01"},{"county_fips":"47097","median_listing_price":"199975","month_date_yyyymm":"2023-08-01"},{"county_fips":"47097","median_listing_price":"209900","month_date_yyyymm":"2023-07-01"},{"county_fips":"47097","median_listing_price":"202475","month_date_yyyymm":"2023-06-01"},{"county_fips":"47097","median_listing_price":"172450","month_date_yyyymm":"2023-05-01"},{"county_fips":"47097","median_listing_price":"139900","month_date_yyyymm":"2023-04-01"},{"county_fips":"47097","median_listing_price":"142000","month_date_yyyymm":"2023-03-01"},{"county_fips":"47097","median_listing_price":"157225","month_date_yyyymm":"2023-02-01"},{"county_fips":"47097","median_listing_price":"161875","month_date_yyyymm":"2023-01-01"},{"county_fips":"47097","median_listing_price":"172450","month_date_yyyymm":"2022-12-01"},{"county_fips":"47097","median_listing_price":"175250","month_date_yyyymm":"2022-11-01"},{"county_fips":"47097","median_listing_price":"183000","month_date_yyyymm":"2022-10-01"},{"county_fips":"47097","median_listing_price":"148750","month_date_yyyymm":"2022-09-01"},{"county_fips":"47097","median_listing_price":"145000","month_date_yyyymm":"2022-08-01"},{"county_fips":"47097","median_listing_price":"157500","month_date_yyyymm":"2022-07-01"},{"county_fips":"47097","median_listing_price":"142475","month_date_yyyymm":"2022-06-01"},{"county_fips":"47097","median_listing_price":"136450","month_date_yyyymm":"2022-05-01"},{"county_fips":"47097","median_listing_price":"79000","month_date_yyyymm":"2022-04-01"},{"county_fips":"47097","median_listing_price":"84500","month_date_yyyymm":"2022-03-01"},{"county_fips":"47097","median_listing_price":"74925","month_date_yyyymm":"2022-02-01"},{"county_fips":"47097","median_listing_price":"78950","month_date_yyyymm":"2022-01-01"},{"county_fips":"47097","median_listing_price":"87705","month_date_yyyymm":"2021-12-01"},{"county_fips":"47097","median_listing_price":"91100","month_date_yyyymm":"2021-11-01"},{"county_fips":"47097","median_listing_price":"86750","month_date_yyyymm":"2021-10-01"},{"county_fips":"47097","median_listing_price":"87725","month_date_yyyymm":"2021-09-01"},{"county_fips":"47097","median_listing_price":"150000","month_date_yyyymm":"2021-08-01"},{"county_fips":"47097","median_listing_price":"149950","month_date_yyyymm":"2021-07-01"},{"county_fips":"47097","median_listing_price":"111975","month_date_yyyymm":"2021-06-01"},{"county_fips":"47097","median_listing_price":"85000","month_date_yyyymm":"2021-05-01"},{"county_fips":"47097","median_listing_price":"90250","month_date_yyyymm":"2021-04-01"},{"county_fips":"47097","median_listing_price":"64950","month_date_yyyymm":"2021-03-01"},{"county_fips":"47097","median_listing_price":"62175","month_date_yyyymm":"2021-02-01"},{"county_fips":"47097","median_listing_price":"72250","month_date_yyyymm":"2021-01-01"},{"county_fips":"47097","median_listing_price":"78900","month_date_yyyymm":"2020-12-01"},{"county_fips":"47097","median_listing_price":"83625","month_date_yyyymm":"2020-11-01"},{"county_fips":"47097","median_listing_price":"78500","month_date_yyyymm":"2020-10-01"},{"county_fips":"47097","median_listing_price":"79500","month_date_yyyymm":"2020-09-01"},{"county_fips":"47097","median_listing_price":"67250","month_date_yyyymm":"2020-08-01"},{"county_fips":"47097","median_listing_price":"76450","month_date_yyyymm":"2020-07-01"},{"county_fips":"47097","median_listing_price":"80450","month_date_yyyymm":"2020-06-01"},{"county_fips":"47097","median_listing_price":"81000","month_date_yyyymm":"2020-05-01"},{"county_fips":"47097","median_listing_price":"90125","month_date_yyyymm":"2020-04-01"},{"county_fips":"47097","median_listing_price":"122950","month_date_yyyymm":"2020-03-01"},{"county_fips":"47097","median_listing_price":"119700","month_date_yyyymm":"2020-02-01"},{"county_fips":"47097","median_listing_price":"101925","month_date_yyyymm":"2020-01-01"},{"county_fips":"47097","median_listing_price":"92750","month_date_yyyymm":"2019-12-01"},{"county_fips":"47097","median_listing_price":"83400","month_date_yyyymm":"2019-11-01"},{"county_fips":"47097","median_listing_price":"85352","month_date_yyyymm":"2019-10-01"},{"county_fips":"47097","median_listing_price":"81466","month_date_yyyymm":"2019-09-01"},{"county_fips":"47097","median_listing_price":"75636","month_date_yyyymm":"2019-08-01"},{"county_fips":"47097","median_listing_price":"74125","month_date_yyyymm":"2019-07-01"},{"county_fips":"47097","median_listing_price":"79450","month_date_yyyymm":"2019-06-01"},{"county_fips":"47097","median_listing_price":"74000","month_date_yyyymm":"2019-05-01"},{"county_fips":"47097","median_listing_price":"74500","month_date_yyyymm":"2019-04-01"},{"county_fips":"47097","median_listing_price":"81143","month_date_yyyymm":"2019-03-01"}]}