{"county_fips":"48253","county_name":"jones, tx","timeseries":[{"county_fips":"48253","median_listing_price":"236200","month_date_yyyymm":"2025-03-01"},{"county_fips":"48253","median_listing_price":"234975","month_date_yyyymm":"2025-02-01"},{"county_fips":"48253","median_listing_price":"187400","month_date_yyyymm":"2025-01-01"},{"county_fips":"48253","median_listing_price":"174900","month_date_yyyymm":"2024-12-01"},{"county_fips":"48253","median_listing_price":"169900","month_date_yyyymm":"2024-11-01"},{"county_fips":"48253","median_listing_price":"172475","month_date_yyyymm":"2024-10-01"},{"county_fips":"48253","median_listing_price":"186825","month_date_yyyymm":"2024-09-01"},{"county_fips":"48253","median_listing_price":"189900","month_date_yyyymm":"2024-08-01"},{"county_fips":"48253","median_listing_price":"201175","month_date_yyyymm":"2024-07-01"},{"county_fips":"48253","median_listing_price":"179900","month_date_yyyymm":"2024-06-01"},{"county_fips":"48253","median_listing_price":"179650","month_date_yyyymm":"2024-05-01"},{"county_fips":"48253","median_listing_price":"179650","month_date_yyyymm":"2024-04-01"},{"county_fips":"48253","median_listing_price":"210000","month_date_yyyymm":"2024-03-01"},{"county_fips":"48253","median_listing_price":"221250","month_date_yyyymm":"2024-02-01"},{"county_fips":"48253","median_listing_price":"234475","month_date_yyyymm":"2024-01-01"},{"county_fips":"48253","median_listing_price":"243950","month_date_yyyymm":"2023-12-01"},{"county_fips":"48253","median_listing_price":"259625","month_date_yyyymm":"2023-11-01"},{"county_fips":"48253","median_listing_price":"236400","month_date_yyyymm":"2023-10-01"},{"county_fips":"48253","median_listing_price":"225000","month_date_yyyymm":"2023-09-01"},{"county_fips":"48253","median_listing_price":"200200","month_date_yyyymm":"2023-08-01"},{"county_fips":"48253","median_listing_price":"182450","month_date_yyyymm":"2023-07-01"},{"county_fips":"48253","median_listing_price":"139475","month_date_yyyymm":"2023-06-01"},{"county_fips":"48253","median_listing_price":"174950","month_date_yyyymm":"2023-05-01"},{"county_fips":"48253","median_listing_price":"160000","month_date_yyyymm":"2023-04-01"},{"county_fips":"48253","median_listing_price":"192250","month_date_yyyymm":"2023-03-01"}]}