{"county_fips":"51770","county_name":"roanoke, va","timeseries":[{"county_fips":"51770","median_listing_price":"234567","month_date_yyyymm":"2025-03-01"},{"county_fips":"51770","median_listing_price":"227438","month_date_yyyymm":"2025-02-01"},{"county_fips":"51770","median_listing_price":"232425","month_date_yyyymm":"2025-01-01"},{"county_fips":"51770","median_listing_price":"239973","month_date_yyyymm":"2024-12-01"},{"county_fips":"51770","median_listing_price":"238262","month_date_yyyymm":"2024-11-01"},{"county_fips":"51770","median_listing_price":"239000","month_date_yyyymm":"2024-10-01"},{"county_fips":"51770","median_listing_price":"244000","month_date_yyyymm":"2024-09-01"},{"county_fips":"51770","median_listing_price":"249700","month_date_yyyymm":"2024-08-01"},{"county_fips":"51770","median_listing_price":"248263","month_date_yyyymm":"2024-07-01"},{"county_fips":"51770","median_listing_price":"234950","month_date_yyyymm":"2024-06-01"},{"county_fips":"51770","median_listing_price":"222150","month_date_yyyymm":"2024-05-01"},{"county_fips":"51770","median_listing_price":"224450","month_date_yyyymm":"2024-04-01"},{"county_fips":"51770","median_listing_price":"210975","month_date_yyyymm":"2024-03-01"},{"county_fips":"51770","median_listing_price":"209963","month_date_yyyymm":"2024-02-01"},{"county_fips":"51770","median_listing_price":"209950","month_date_yyyymm":"2024-01-01"},{"county_fips":"51770","median_listing_price":"222450","month_date_yyyymm":"2023-12-01"},{"county_fips":"51770","median_listing_price":"217461","month_date_yyyymm":"2023-11-01"},{"county_fips":"51770","median_listing_price":"217450","month_date_yyyymm":"2023-10-01"},{"county_fips":"51770","median_listing_price":"209900","month_date_yyyymm":"2023-09-01"},{"county_fips":"51770","median_listing_price":"209938","month_date_yyyymm":"2023-08-01"},{"county_fips":"51770","median_listing_price":"230000","month_date_yyyymm":"2023-07-01"},{"county_fips":"51770","median_listing_price":"230938","month_date_yyyymm":"2023-06-01"},{"county_fips":"51770","median_listing_price":"227875","month_date_yyyymm":"2023-05-01"},{"county_fips":"51770","median_listing_price":"229950","month_date_yyyymm":"2023-04-01"},{"county_fips":"51770","median_listing_price":"214000","month_date_yyyymm":"2023-03-01"},{"county_fips":"51770","median_listing_price":"213725","month_date_yyyymm":"2023-02-01"},{"county_fips":"51770","median_listing_price":"216113","month_date_yyyymm":"2023-01-01"},{"county_fips":"51770","median_listing_price":"219500","month_date_yyyymm":"2022-12-01"},{"county_fips":"51770","median_listing_price":"204500","month_date_yyyymm":"2022-11-01"},{"county_fips":"51770","median_listing_price":"199950","month_date_yyyymm":"2022-10-01"},{"county_fips":"51770","median_listing_price":"204950","month_date_yyyymm":"2022-09-01"},{"county_fips":"51770","median_listing_price":"192475","month_date_yyyymm":"2022-08-01"},{"county_fips":"51770","median_listing_price":"199900","month_date_yyyymm":"2022-07-01"},{"county_fips":"51770","median_listing_price":"203499","month_date_yyyymm":"2022-06-01"},{"county_fips":"51770","median_listing_price":"201725","month_date_yyyymm":"2022-05-01"},{"county_fips":"51770","median_listing_price":"199950","month_date_yyyymm":"2022-04-01"},{"county_fips":"51770","median_listing_price":"187475","month_date_yyyymm":"2022-03-01"},{"county_fips":"51770","median_listing_price":"181588","month_date_yyyymm":"2022-02-01"},{"county_fips":"51770","median_listing_price":"179325","month_date_yyyymm":"2022-01-01"},{"county_fips":"51770","median_listing_price":"185950","month_date_yyyymm":"2021-12-01"},{"county_fips":"51770","median_listing_price":"192300","month_date_yyyymm":"2021-11-01"},{"county_fips":"51770","median_listing_price":"194900","month_date_yyyymm":"2021-10-01"},{"county_fips":"51770","median_listing_price":"180588","month_date_yyyymm":"2021-09-01"},{"county_fips":"51770","median_listing_price":"177425","month_date_yyyymm":"2021-08-01"},{"county_fips":"51770","median_listing_price":"169950","month_date_yyyymm":"2021-07-01"},{"county_fips":"51770","median_listing_price":"187238","month_date_yyyymm":"2021-06-01"},{"county_fips":"51770","median_listing_price":"169725","month_date_yyyymm":"2021-05-01"},{"county_fips":"51770","median_listing_price":"159950","month_date_yyyymm":"2021-04-01"},{"county_fips":"51770","median_listing_price":"166225","month_date_yyyymm":"2021-03-01"},{"county_fips":"51770","median_listing_price":"181975","month_date_yyyymm":"2021-02-01"},{"county_fips":"51770","median_listing_price":"169900","month_date_yyyymm":"2021-01-01"},{"county_fips":"51770","median_listing_price":"168700","month_date_yyyymm":"2020-12-01"},{"county_fips":"51770","median_listing_price":"189000","month_date_yyyymm":"2020-11-01"},{"county_fips":"51770","median_listing_price":"175000","month_date_yyyymm":"2020-10-01"},{"county_fips":"51770","median_listing_price":"189938","month_date_yyyymm":"2020-09-01"},{"county_fips":"51770","median_listing_price":"194950","month_date_yyyymm":"2020-08-01"},{"county_fips":"51770","median_listing_price":"196675","month_date_yyyymm":"2020-07-01"},{"county_fips":"51770","median_listing_price":"194950","month_date_yyyymm":"2020-06-01"},{"county_fips":"51770","median_listing_price":"169900","month_date_yyyymm":"2020-05-01"},{"county_fips":"51770","median_listing_price":"149925","month_date_yyyymm":"2020-04-01"},{"county_fips":"51770","median_listing_price":"149825","month_date_yyyymm":"2020-03-01"},{"county_fips":"51770","median_listing_price":"149250","month_date_yyyymm":"2020-02-01"},{"county_fips":"51770","median_listing_price":"145750","month_date_yyyymm":"2020-01-01"},{"county_fips":"51770","median_listing_price":"142125","month_date_yyyymm":"2019-12-01"},{"county_fips":"51770","median_listing_price":"138475","month_date_yyyymm":"2019-11-01"},{"county_fips":"51770","median_listing_price":"148932","month_date_yyyymm":"2019-10-01"},{"county_fips":"51770","median_listing_price":"145523","month_date_yyyymm":"2019-09-01"},{"county_fips":"51770","median_listing_price":"140409","month_date_yyyymm":"2019-08-01"},{"county_fips":"51770","median_listing_price":"138238","month_date_yyyymm":"2019-07-01"},{"county_fips":"51770","median_listing_price":"140000","month_date_yyyymm":"2019-06-01"},{"county_fips":"51770","median_listing_price":"140462","month_date_yyyymm":"2019-05-01"},{"county_fips":"51770","median_listing_price":"136822","month_date_yyyymm":"2019-04-01"},{"county_fips":"51770","median_listing_price":"137600","month_date_yyyymm":"2019-03-01"}]}